[
  {
    "thumbnail": "images/newsletter/newsletter1.png",
    "title": "Transforming to Plastics Circularity",
    "excerpt": "Exploring regional and youth-led efforts to build sustainable plastic systems through innovation.",
    "source": "From STEAM Newsletter",
    "date": "September 2022",
    "link": "https://www.steamplatform.org/newsletter/transforming-to-plastics-circularity"
  },
  {
    "thumbnail": "images/newsletter/newsletter2.png",
    "title": "Empowering High School Youth Leaders in Developing Solutions for Thailand Waste Problem",
    "excerpt": "Youth leaders tackle Thailand's waste issues using circular economy frameworks and innovation.",
    "source": "From STEAM Newsletter",
    "date": " April – July  2022",
    "link": "https://www.steamplatform.org/newsletter/empowering-high-school-youth-leaders-in-developing-solutions-for-thailand-waste-problem"
  },
  {
    "thumbnail": "images/newsletter/newsletter3.png",
    "title": "Innovation in Processing Plastics Waste Enabling SDGs 2030",
    "excerpt": "Highlighting startup innovations that contribute to plastic waste circularity and the SDGs.",
    "source": "From STEAM Newsletter",
    "date": "March 2022",
    "link": "https://www.steamplatform.org/newsletter/innovation-in-processing-plastics-waste-enabling-sdgs-2030"
  },
  {
    "thumbnail": "images/newsletter/newsletter4.png",
    "title": "Innovations for Plastics Circularity",
    "excerpt": "Breakthrough technologies and policies improving plastics circularity in Southeast Asia.",
    "source": "From STEAM Newsletter",
    "date": " November – December 2021",
    "link": "https://www.steamplatform.org/newsletter/innovations-for-plastics-circularity"
  },
  {
    "thumbnail": "images/newsletter/newsletter5.png",
    "title": "Thailand Plastic Ghostbusters",
    "excerpt": "STEAM youth participants creatively tackled plastic pollution in local communities.",
    "source": "From STEAM Newsletter",
    "date": "October 2021",
    "link": "https://www.steamplatform.org/newsletter/thailand-plastic-ghostbusters"
  },
  {
    "thumbnail": "images/newsletter/newsletter6.png",
    "title": "What Drives the Transformation of a Circular Economy?",
    "excerpt": "Key forces like education, policy, and business that push circular transition forward.",
    "source": "From STEAM Newsletter",
    "date": "April – May 2021",
    "link": "https://www.steamplatform.org/newsletter/what-drives-the-transformation-of-a-circular-economy%3F"
  },
  {
    "thumbnail": "images/newsletter/newsletter7.png",
    "title": "Plastic Packaging Circularity Entrepreneurship Highlight in Thailand",
    "excerpt": "Entrepreneurs pioneering reuse and recycling of plastic packaging in Thailand.",
    "source": "From STEAM Newsletter",
    "date": "March 2021",
    "link": "https://www.steamplatform.org/newsletter/plastic-packaging-circularity-entrepreneurship-highlight-in-thailand"
  },
  {
    "thumbnail": "images/newsletter/newsletter8.png",
    "title": "Sustainable Business Features: Circular Economy Leadership & Partnership in Food Industry, Thailand",
    "excerpt": "Corporate and institutional efforts toward sustainable food systems in Thailand.",
    "source": "From STEAM Newsletter",
    "date": "January – February 2021",
    "link": "https://www.steamplatform.org/newsletter/sustainable-business-features%3A-circular-economy-leadership-%26-partnership-in-food-industry%2C-thailand"
  },
  {
    "thumbnail": "images/newsletter/newsletter9.png",
    "title": "Thailand Circular Economy Practices: Leadership and Partnership",
    "excerpt": "Examples of Thai leadership and cross-sector collaboration in circular practices.",
    "source": "From STEAM Newsletter",
    "date": "December 2020",
    "link": "https://www.steamplatform.org/newsletter/thailand-circular-economy-practices%3A-leadership-and-partnership-"
  },
  {
    "thumbnail": "images/newsletter/newsletter10.png",
    "title": "Circular Economy on Textile & Fashion",
    "excerpt": "Fashion and textile industries rethinking materials and waste in Southeast Asia.",
    "source": "From STEAM Newsletter",
    "date": "November 2020",
    "link": "https://www.steamplatform.org/newsletter/circular-economy-on-textile-%26-fashion-"
  },
  {
    "thumbnail": "images/newsletter/newsletter11.png",
    "title": "Sustainable Food & Agriculture 4.0",
    "excerpt": "Digital innovations shaping the future of agriculture in a circular economy.",
    "source": "From STEAM Newsletter",
    "date": "December 2019",
    "link": "https://www.steamplatform.org/newsletter/sustainable-food-%26-agriculture-4.0"
  }
]